{
    "$jsonSchema": {
      "bsonType": "object",
      "required": [
        "admission_id",
        "patient_id",
        "name",
        "age",
        "gender",
        "blood_type",
        "medical_condition",
        "date_of_admission",
        "doctor",
        "hospital",
        "insurance_provider",
        "billing_amount",
        "room_number",
        "admission_type",
        "discharge_date",
        "medication",
        "test_results"
      ],
      "properties": {
        "admission_id" : {
            "bsonType" : "string",
            "pattern" : "^[0-9]+_[0-9]{4}-[0-9]{2}-[0-9]{2}$",
            "description" : "Unique identifier for each patient admission, created by combining patient_id and date_of_admission"
        },
        "patient_id" : {
            "bsonType" : "int",
            "description" : "Unique identifier for each patient, created via hashing the name, age, gender and blood_type of a patient"
        },
        "name": {
          "bsonType": "string",
          "description": "Patient's name must be a string."
        },
        "age": {
          "bsonType": "string",
          "pattern": "^[0-9]+$",
          "description": "Age must be a string containing numeric values only."
        },
        "gender": {
          "bsonType": "string",
          "enum": ["Male", "Female", "Other"],
          "description": "Gender must be 'Male', 'Female', or 'Other'."
        },
        "blood_type": {
          "bsonType": "string",
          "enum": ["A+", "A-", "B+", "B-", "AB+", "AB-", "O+", "O-"],
          "description": "Blood type must be a valid blood type."
        },
        "medical_condition": {
          "bsonType": "string",
          "description": "Medical condition must be a string."
        },
        "date_of_admission": {
          "bsonType": "string",
          "pattern": "^\\d{4}-\\d{2}-\\d{2}$",
          "description": "Date of admission must be in the format YYYY-MM-DD."
        },
        "doctor": {
          "bsonType": "string",
          "description": "Doctor's name must be a string."
        },
        "hospital": {
          "bsonType": "string",
          "description": "Hospital name must be a string."
        },
        "insurance_provider": {
          "bsonType": "string",
          "description": "Insurance provider name must be a string."
        },
        "billing_amount": {
          "bsonType": "string",
          "pattern": "^[0-9]+(\\.[0-9]+)?$",
          "description": "Billing amount must be a string containing numeric values."
        },
        "room_number": {
          "bsonType": "string",
          "pattern": "^[0-9]+$",
          "description": "Room number must be a string containing numeric values."
        },
        "admission_type": {
          "bsonType": "string",
          "enum": ["Emergency", "Elective", "Urgent"],
          "description": "Admission type must be either 'Emergency', 'Elective' or 'Urgent'."
        },
        "discharge_date": {
          "bsonType": "string",
          "pattern": "^\\d{4}-\\d{2}-\\d{2}$",
          "description": "Discharge date must be in the format YYYY-MM-DD."
        },
        "medication": {
          "bsonType": "string",
          "description": "Medication must be a string."
        },
        "test_results": {
          "bsonType": "string",
          "enum": ["Normal", "Abnormal", "Inconclusive"],
          "description": "Test results must be 'Normal', 'Abnormal', or 'Inconclusive'."
        }
      }
    }
  }
  